scuse/__init__.py
scuse-0.2.dist-info/LICENCE.txt
scuse-0.2.dist-info/METADATA
scuse-0.2.dist-info/WHEEL
scuse-0.2.dist-info/top_level.txt
scuse-0.2.dist-info/RECORD
